datacleanx/__init__.py
datacleanx/cleaner.py
datacleanx/cli.py
datacleanx/encoder.py
datacleanx/feature_cleaner.py
datacleanx/imputer.py
datacleanx/outliers.py
datacleanx/report.py
datacleanx/types.py
datacleanx/utils.py
datacleanx-0.1.0.dist-info/LICENSE
datacleanx-0.1.0.dist-info/METADATA
datacleanx-0.1.0.dist-info/WHEEL
datacleanx-0.1.0.dist-info/entry_points.txt
datacleanx-0.1.0.dist-info/RECORD
