Metadata-Version: 2.3
Name: datacleanx
Version: 0.1.0
Summary: Fast data cleaning engine for ML projects
License: MIT
Keywords: data-cleaning,ML,CLI,preprocessing
Author: Esther
Author-email: esther@example.com
Requires-Python: >=3.12,<4.0
Classifier: License :: OSI Approved :: MIT License
Classifier: Programming Language :: Python :: 3
Classifier: Programming Language :: Python :: 3.12
Classifier: Programming Language :: Python :: 3.13
Requires-Dist: numpy (>=1.26,<2.0)
Requires-Dist: pandas (>=2.2,<3.0)
Requires-Dist: scikit-learn (>=1.5,<2.0)
Project-URL: Homepage, https://github.com/essiebx/datacleanx
Project-URL: Repository, https://github.com/essiebx/datacleanx
